{"version": 0.6, "generator": "Overpass API 0.7.62.11 87bfad18", "osm3s": {"timestamp_osm_base": "2026-05-01T03:22:51Z", "timestamp_areas_base": "2026-04-30T15:41:15Z", "copyright": "The data included in this document is from www.openstreetmap.org. The data is made available under ODbL."}, "elements": [{"type": "relation", "id": 4107185, "center": {"lat": 41.5133878, "lon": 140.8757672}, "tags": {"admin_level": "7", "boundary": "administrative", "name": "大間町", "name:en": "Oma", "name:ja": "大間町", "name:ja-Hira": "おおままち", "name:ja-Latn": "Ōma-machi", "name:ko": "오마마치", "name:ru": "Ома", "name:th": "โอมะ", "name:uk": "Ома", "name:zh": "大間町", "name:zh-Hans": "大间町", "name:zh-Hant": "大間町", "ref": "024236", "type": "boundary", "wikidata": "Q1362378", "wikipedia": "ja:大間町"}}, {"type": "relation", "id": 4107186, "center": {"lat": 41.5118259, "lon": 141.1213887}, "tags": {"admin_level": "7", "boundary": "administrative", "name": "風間浦村", "name:en": "Kazamaura", "name:ja": "風間浦村", "name:ja-Hira": "かざまうらむら", "name:ja-Latn": "Kazamaura-mura", "name:ko": "가자마우라무라", "name:ru": "Кадзамаура", "name:th": "คาซามาอูระ", "name:uk": "Кадзамаура", "name:zh": "風間浦村", "name:zh-Hans": "风间浦村", "name:zh-Hant": "風間浦村", "ref": "024252", "type": "boundary", "wikidata": "Q1349460", "wikipedia": "ja:風間浦村"}}, {"type": "relation", "id": 4107191, "center": {"lat": 41.3012417, "lon": 141.0172602}, "tags": {"admin_level": "7", "boundary": "administrative", "name": "むつ市", "name:en": "Mutsu", "name:ja": "むつ市", "name:ja-Hira": "むつし", "name:ja-Latn": "Mutsu-shi", "name:ko": "무쓰시", "name:pl": "Mutsu", "name:ru": "Муцу", "name:th": "มุตสึ", "name:uk": "Муцу", "name:zh": "陸奧市", "name:zh-Hans": "陆奥市", "name:zh-Hant": "陸奧市", "ref": "022080", "type": "boundary", "wikidata": "Q641992", "wikipedia": "ja:むつ市"}}, {"type": "relation", "id": 4107196, "center": {"lat": 41.3657585, "lon": 140.7446107}, "tags": {"admin_level": "7", "boundary": "administrative", "name": "佐井村", "name:en": "Sai", "name:ja": "佐井村", "name:ja-Hira": "さいむら", "name:ja-Latn": "Sai-mura", "name:ko": "사이무라", "name:ru": "Саи", "name:th": "ซาอิ", "name:uk": "Сай", "name:zh": "佐井村", "name:zh-Hans": "佐井村", "name:zh-Hant": "佐井村", "ref": "024261", "type": "boundary", "wikidata": "Q1362393", "wikipedia": "ja:佐井村"}}, {"type": "relation", "id": 4107205, "center": {"lat": 41.3544378, "lon": 141.4812342}, "tags": {"admin_level": "7", "boundary": "administrative", "name": "東通村", "name:en": "Higashidori", "name:ja": "東通村", "name:ja-Hira": "ひがしどおりむら", "name:ja-Latn": "Higashidōri-mura", "name:ko": "히가시도리무라", "name:ru": "Хигасидори", "name:th": "ฮิงาชิโดริ", "name:uk": "Хіґасідорі", "name:zh": "東通村", "name:zh-Hans": "东通村", "name:zh-Hant": "東通村", "ref": "024244", "type": "boundary", "wikidata": "Q1349156", "wikipedia": "ja:東通村"}}, {"type": "relation", "id": 4107217, "center": {"lat": 41.0664322, "lon": 141.2171743}, "tags": {"admin_level": "7", "boundary": "administrative", "name": "横浜町", "name:en": "Yokohama", "name:ja": "横浜町", "name:ja-Hira": "よこはままち", "name:ja-Latn": "Yokohama-machi", "name:ko": "요코하마마치", "name:ru": "Иокогама", "name:th": "โยโกฮามะ", "name:uk": "Йокохама", "name:zh": "橫濱町", "name:zh-Hans": "横滨町", "name:zh-Hant": "橫濱町", "ref": "024066", "type": "boundary", "wikidata": "Q1205910", "wikipedia": "ja:横浜町"}}, {"type": "relation", "id": 4107221, "center": {"lat": 40.9977722, "lon": 141.4524725}, "tags": {"admin_level": "7", "boundary": "administrative", "name": "六ヶ所村", "name:en": "Rokkasho", "name:ja": "六ヶ所村", "name:ja-Hira": "ろっかしょむら", "name:ja-Latn": "Rokkasho-mura", "name:ko": "롯카쇼무라", "name:ru": "Роккасё", "name:th": "รกกาโชะ", "name:uk": "Роккасьо", "name:zh": "六所村", "name:zh-Hans": "六所村", "name:zh-Hant": "六所村", "ref": "024112", "type": "boundary", "wikidata": "Q1362335", "wikipedia": "ja:六ヶ所村"}}, {"type": "relation", "id": 4107222, "center": {"lat": 40.9148938, "lon": 141.1485925}, "tags": {"admin_level": "7", "boundary": "administrative", "name": "野辺地町", "name:en": "Noheji", "name:ja": "野辺地町", "name:ja-Hira": "のへじまち", "name:ja-Latn": "Noheji-machi", "name:ko": "노헤지마치", "name:pl": "Noheji", "name:ru": "Нохедзи", "name:th": "โนเฮจิ", "name:uk": "Нохедзі", "name:zh": "野邊地町", "name:zh-Hans": "野边地町", "name:zh-Hant": "野邊地町", "ref": "024015", "type": "boundary", "wikidata": "Q1362344", "wikipedia": "ja:野辺地町"}}, {"type": "relation", "id": 4107223, "center": {"lat": 40.7981126, "lon": 141.1873325}, "tags": {"admin_level": "7", "boundary": "administrative", "name": "東北町", "name:cs": "Tóhoku", "name:en": "Tohoku", "name:ja": "東北町", "name:ja-Hira": "とうほくまち", "name:ja-Latn": "Tohoku-chō", "name:ko": "도호쿠초", "name:ru": "Тохоку", "name:th": "โทโฮกุ", "name:uk": "Тохоку", "name:zh": "東北町", "name:zh-Hans": "东北町", "name:zh-Hant": "東北町", "population": "17472", "ref": "024082", "type": "boundary", "wikidata": "Q1194394", "wikipedia": "ja:東北町"}}, {"type": "relation", "id": 4107227, "center": {"lat": 40.7767094, "lon": 141.503092}, "tags": {"admin_level": "7", "boundary": "administrative", "name": "三沢市", "name:en": "Misawa", "name:ja": "三沢市", "name:ja-Hira": "みさわし", "name:ja-Latn": "Misawa-shi", "name:ko": "미사와시", "name:pl": "Misawa", "name:ru": "Мисава", "name:th": "มิซาวะ", "name:uk": "Місава", "name:zh": "三澤市", "name:zh-Hans": "三泽市", "name:zh-Hant": "三澤市", "population": "39152", "ref": "022071", "source:population": "Census 2020", "type": "boundary", "wikidata": "Q496401", "wikipedia": "ja:三沢市"}}, {"type": "relation", "id": 4107257, "center": {"lat": 40.7248695, "lon": 141.0863575}, "tags": {"admin_level": "7", "boundary": "administrative", "name": "七戸町", "name:en": "Shichinohe", "name:ja": "七戸町", "name:ja-Hira": "しちのへまち", "name:ja-Latn": "Shichinohe-machi", "name:ko": "시치노헤마치", "name:ru": "Ситинохе", "name:th": "ชิจิโนเฮะ", "name:uk": "Сітінохе", "name:zh": "七戶町", "name:zh-Hans": "七户町", "name:zh-Hant": "七戶町", "population": "15207", "ref": "024023", "type": "boundary", "wikidata": "Q1349448", "wikipedia": "ja:七戸町"}}, {"type": "relation", "id": 4107258, "center": {"lat": 40.9473264, "lon": 140.9367126}, "tags": {"admin_level": "7", "boundary": "administrative", "name": "平内町", "name:en": "Hiranai", "name:ja": "平内町", "name:ja-Hira": "ひらないまち", "name:ja-Latn": "Hiranai-machi", "name:ko": "히라나이마치", "name:pl": "Hiranai", "name:ru": "Хиранай", "name:th": "ฮิราไน", "name:uk": "Хіранай", "name:zh": "平內町", "name:zh-Hans": "平内町", "name:zh-Hant": "平內町", "ref": "023019", "type": "boundary", "wikidata": "Q1206422", "wikipedia": "ja:平内町"}}, {"type": "relation", "id": 4107331, "center": {"lat": 40.561363, "lon": 141.0779825}, "tags": {"admin_level": "7", "boundary": "administrative", "name": "十和田市", "name:ar": "تووادا، آوموري", "name:de": "Towada", "name:en": "Towada", "name:es": "Towada", "name:fr": "Towada", "name:ja": "十和田市", "name:ja-Hira": "とわだし", "name:ja-Latn": "Towada-shi", "name:ko": "도와다시", "name:pl": "Towada", "name:ru": "Товада", "name:th": "โทวาดะ", "name:uk": "Товада", "name:zh": "十和田市", "name:zh-Hans": "十和田市", "name:zh-Hant": "十和田市", "population": "60378", "ref": "022063", "source:population": "Census 2020", "start_date": "1956-10-10", "type": "boundary", "wikidata": "Q646818", "wikimedia_commons": "Category:Towada, Aomori", "wikipedia": "ja:十和田市"}}, {"type": "relation", "id": 4107332, "center": {"lat": 40.631818, "lon": 141.319458}, "tags": {"admin_level": "7", "boundary": "administrative", "name": "六戸町", "name:en": "Rokunohe", "name:ja": "六戸町", "name:ja-Hira": "ろくのへまち", "name:ja-Latn": "Rokunohe-machi", "name:ko": "로쿠노헤마치", "name:ru": "Рокунохе", "name:th": "โรกูโนเฮะ", "name:uk": "Рокунохе", "name:zh": "六戶町", "name:zh-Hans": "六户町", "name:zh-Hant": "六戶町", "ref": "024058", "type": "boundary", "wikidata": "Q1206630", "wikipedia": "ja:六戸町"}}, {"type": "relation", "id": 4107337, "center": {"lat": 40.7880795, "lon": 140.750616}, "tags": {"admin_level": "7", "boundary": "administrative", "name": "青森市", "name:cs": "Aomori", "name:en": "Aomori", "name:it": "Aomori", "name:ja": "青森市", "name:ja-Hira": "あおもりし", "name:ja-Latn": "Aomori-shi", "name:ko": "아오모리시", "name:pl": "Aomori", "name:pt": "Aomori", "name:ru": "Аомори", "name:th": "อาโอโมริ", "name:uk": "Аоморі", "name:zh": "青森市", "name:zh-Hans": "青森市", "name:zh-Hant": "青森市", "population": "275192", "ref": "022012", "source:population": "Census 2020", "type": "boundary", "wikidata": "Q146790", "wikipedia": "ja:青森市"}}, {"type": "relation", "id": 4107352, "center": {"lat": 40.5030525, "lon": 141.301062}, "tags": {"admin_level": "7", "boundary": "administrative", "name": "五戸町", "name:en": "Gonohe", "name:ja": "五戸町", "name:ja-Hira": "ごのへまち", "name:ja-Latn": "Gonohe-machi", "name:ko": "고노헤마치", "name:ru": "Гонохе", "name:th": "โกโนเฮะ", "name:uk": "Ґонохе", "name:zh": "五戶町", "name:zh-Hans": "五户町", "name:zh-Hant": "五戶町", "population": "16935", "ref": "024422", "type": "boundary", "wikidata": "Q1362324", "wikipedia": "ja:五戸町"}}, {"type": "relation", "id": 4107406, "center": {"lat": 40.6345862, "lon": 141.4914786}, "tags": {"admin_level": "7", "boundary": "administrative", "name": "おいらせ町", "name:en": "Oirase", "name:ja": "おいらせ町", "name:ja-Hira": "おいらせちょう", "name:ja-Latn": "Oirase-chō", "name:ko": "오이라세초", "name:ru": "Оирасе", "name:th": "โออิราเซะ", "name:uk": "Ойрасе", "name:zh": "奧入瀨町", "name:zh-Hans": "奥入濑町", "name:zh-Hant": "奧入瀨町", "population": "24307", "ref": "024121", "type": "boundary", "wikidata": "Q1349124", "wikipedia": "ja:おいらせ町"}}, {"type": "relation", "id": 4107414, "center": {"lat": 40.5345874, "lon": 141.6062213}, "tags": {"admin_level": "7", "boundary": "administrative", "name": "八戸市", "name:cs": "Hačinohe", "name:en": "Hachinohe", "name:ja": "八戸市", "name:ja-Hira": "はちのへし", "name:ja-Latn": "Hachinohe-shi", "name:ko": "하치노헤시", "name:pl": "Hachinohe", "name:ru": "Хатинохе", "name:th": "ฮาจิโนเฮะ", "name:uk": "Хатінохе", "name:zh": "八戶市", "name:zh-Hans": "八户市", "name:zh-Hant": "八戶市", "population": "223415", "ref": "022039", "source:population": "Census 2020", "type": "boundary", "wikidata": "Q191914", "wikipedia": "ja:八戸市", "wikipedia:en": "Hachinohe"}}, {"type": "relation", "id": 4107422, "center": {"lat": 40.516726, "lon": 140.6944698}, "tags": {"admin_level": "7", "boundary": "administrative", "name": "平川市", "name:en": "Hirakawa", "name:ja": "平川市", "name:ja-Hira": "ひらかわし", "name:ja-Latn": "Hirakawa-shi", "name:ko": "히라카와시", "name:pl": "Hirakawa", "name:ru": "Хиракава", "name:th": "ฮิรากาวะ", "name:uk": "Хіракава", "name:zh": "平川市", "name:zh-Hans": "平川市", "name:zh-Hant": "平川市", "population": "30567", "ref": "022101", "source:population": "Census 2020", "type": "boundary", "wikidata": "Q695930", "wikipedia": "ja:平川市"}}, {"type": "relation", "id": 4107423, "center": {"lat": 40.6134986, "lon": 140.7049525}, "tags": {"addr:city": "黒石市", "addr:province": "青森県", "admin_level": "7", "boundary": "administrative", "name": "黒石市", "name:en": "Kuroishi", "name:ja": "黒石市", "name:ja-Hira": "くろいしし", "name:ja-Latn": "Kuroishi-shi", "name:ko": "구로이시시", "name:pl": "Kuroishi", "name:ru": "Куроиси", "name:th": "คูโรอิชิ", "name:uk": "Куроїсі", "name:zh": "黑石市", "name:zh-Hans": "黑石市", "name:zh-Hant": "黑石市", "population": "31946", "ref": "022047", "source:population": "Census 2020", "type": "boundary", "wikidata": "Q496412", "wikipedia": "ja:黒石市"}}, {"type": "relation", "id": 4107427, "center": {"lat": 40.681606, "lon": 140.5197905}, "tags": {"admin_level": "7", "boundary": "administrative", "name": "藤崎町", "name:en": "Fujisaki", "name:ja": "藤崎町", "name:ja-Hira": "ふじさきまち", "name:ja-Latn": "Fujisaki-machi", "name:ko": "후지사키마치", "name:pl": "Fujisaki", "name:ru": "Фудзисаки", "name:th": "ฟูจิซากิ", "name:uk": "Фудзісакі", "name:zh": "藤崎町", "name:zh-Hans": "藤崎町", "name:zh-Hant": "藤崎町", "population": "14913", "ref": "023612", "type": "boundary", "wikidata": "Q1348951", "wikipedia": "ja:藤崎町"}}, {"type": "relation", "id": 4107430, "center": {"lat": 40.713221, "lon": 140.48152}, "tags": {"admin_level": "7", "boundary": "administrative", "name": "板柳町", "name:en": "Itayanagi", "name:ja": "板柳町", "name:ja-Hira": "いたやなぎまち", "name:ja-Latn": "Itayanagi-machi", "name:ko": "이타야나기마치", "name:pl": "Itayanagi", "name:ru": "Итаянаги", "name:th": "อิตายานางิ", "name:uk": "Ітаянаґі", "name:zh": "板柳町", "name:zh-Hans": "板柳町", "name:zh-Hant": "板柳町", "ref": "023817", "type": "boundary", "wikidata": "Q1347574", "wikipedia": "ja:板柳町"}}, {"type": "relation", "id": 4107435, "center": {"lat": 40.9286075, "lon": 140.3645791}, "tags": {"admin_level": "7", "boundary": "administrative", "name": "五所川原市", "name:en": "Goshogawara", "name:ja": "五所川原市", "name:ja-Hira": "ごしょがわらし", "name:ja-Latn": "Goshogawara-shi", "name:ko": "고쇼가와라시", "name:pl": "Goshogawara", "name:ru": "Госёгавара", "name:th": "โกโชงาวาระ", "name:uk": "Ґосьоґавара", "name:zh": "五所川原市", "name:zh-Hans": "五所川原市", "name:zh-Hant": "五所川原市", "ref": "022055", "type": "boundary", "wikidata": "Q496702", "wikipedia": "ja:五所川原市"}}, {"type": "relation", "id": 4107436, "center": {"lat": 40.9923775, "lon": 140.6382177}, "tags": {"admin_level": "7", "boundary": "administrative", "name": "蓬田村", "name:en": "Yomogita", "name:ja": "蓬田村", "name:ja-Hira": "よもぎたむら", "name:ja-Latn": "Yomogita-mura", "name:ko": "요모기타무라", "name:pl": "Yomogita", "name:ru": "Йомогита", "name:th": "โยโมงิตะ", "name:uk": "Йомоґіта", "name:zh": "蓬田村", "name:zh-Hans": "蓬田村", "name:zh-Hant": "蓬田村", "ref": "023043", "type": "boundary", "wikidata": "Q1347692", "wikipedia": "ja:蓬田村"}}, {"type": "relation", "id": 4107452, "center": {"lat": 41.0929476, "lon": 140.1740488}, "tags": {"admin_level": "7", "boundary": "administrative", "name": "中泊町", "name:en": "Nakadomari", "name:ja": "中泊町", "name:ja-Hira": "なかどまりまち", "name:ja-Latn": "Nakadomari-machi", "name:ko": "나카도마리마치", "name:pl": "Nakadomari", "name:ru": "Накадомари", "name:th": "นากาโดมาริ", "name:uk": "Накадомарі", "name:zh": "中泊町", "name:zh-Hans": "中泊町", "name:zh-Hant": "中泊町", "ref": "023876", "type": "boundary", "wikidata": "Q1347669", "wikipedia": "ja:中泊町"}}, {"type": "relation", "id": 4107459, "center": {"lat": 41.2123414, "lon": 140.4977053}, "tags": {"admin_level": "7", "boundary": "administrative", "name": "外ヶ浜町", "name:en": "Sotogahama", "name:ja": "外ヶ浜町", "name:ja-Hira": "そとがはままち", "name:ja-Latn": "Sotogahama-machi", "name:ko": "소토가하마마치", "name:pl": "Sotogahama", "name:ru": "Сотогахама", "name:th": "โซโตงาฮามะ", "name:uk": "Сотоґахама", "name:zh": "外濱町", "name:zh-Hans": "外滨町", "name:zh-Hant": "外濱町", "ref": "023078", "type": "boundary", "wikidata": "Q1347655", "wikipedia": "ja:外ヶ浜町"}}, {"type": "relation", "id": 4107469, "center": {"lat": 41.2665245, "lon": 140.5294315}, "tags": {"admin_level": "7", "boundary": "administrative", "name": "今別町", "name:en": "Imabetsu", "name:ja": "今別町", "name:ja-Hira": "いまべつまち", "name:ja-Latn": "Imabetsu-machi", "name:ko": "이마베쓰마치", "name:ru": "Имабецу", "name:th": "อิมาเบ็ตสึ", "name:uk": "Імабецу", "name:zh": "今别町", "name:zh-Hans": "今别町", "name:zh-Hant": "今別町", "ref": "023035", "type": "boundary", "wikidata": "Q1362366", "wikipedia": "ja:今別町"}}, {"type": "relation", "id": 4107487, "center": {"lat": 40.88562, "lon": 140.2322977}, "tags": {"admin_level": "7", "boundary": "administrative", "name": "つがる市", "name:en": "Tsugaru", "name:ja": "つがる市", "name:ja-Hira": "つがるし", "name:ja-Latn": "Tsugaru-shi", "name:ko": "쓰가루시", "name:pl": "Tsugaru", "name:ru": "Цугару", "name:th": "สึงารุ", "name:uk": "Цуґару", "name:zh": "津輕市", "name:zh-Hans": "津轻市", "name:zh-Hant": "津輕市", "ref": "022098", "type": "boundary", "wikidata": "Q372517", "wikipedia": "ja:つがる市"}}, {"type": "relation", "id": 4107490, "center": {"lat": 40.7556875, "lon": 140.420523}, "tags": {"admin_level": "7", "boundary": "administrative", "name": "鶴田町", "name:en": "Tsuruta", "name:ja": "鶴田町", "name:ja-Hira": "つるたまち", "name:ja-Latn": "Tsuruta-machi", "name:ko": "쓰루타마치", "name:pl": "Tsuruta", "name:ru": "Цурута", "name:th": "สึรูตะ", "name:uk": "Цурута", "name:zh": "鶴田町", "name:zh-Hans": "鹤田町", "name:zh-Hant": "鶴田町", "ref": "023841", "type": "boundary", "wikidata": "Q2358964", "wikipedia": "ja:鶴田町"}}, {"type": "relation", "id": 4107507, "center": {"lat": 40.614489, "lon": 140.376712}, "tags": {"admin_level": "7", "boundary": "administrative", "name": "弘前市", "name:en": "Hirosaki", "name:fr": "Hirosaki", "name:it": "Hirosaki", "name:ja": "弘前市", "name:ja-Hira": "ひろさきし", "name:ja-Latn": "Hirosaki-shi", "name:ko": "히로사키시", "name:pl": "Hirosaki", "name:ru": "Хиросаки", "name:th": "ฮิโรซากิ", "name:uk": "Хіросакі", "name:zh": "弘前市", "name:zh-Hans": "弘前市", "name:zh-Hant": "弘前市", "population": "168466", "ref": "022021", "source:population": "Census 2020", "type": "boundary", "wikidata": "Q194087", "wikimedia_commons": "Category:Hirosaki, Aomori", "wikipedia": "ja:弘前市"}}, {"type": "relation", "id": 4107525, "center": {"lat": 40.6735292, "lon": 140.2023493}, "tags": {"admin_level": "7", "boundary": "administrative", "name": "鰺ヶ沢町", "name:en": "Ajigasawa", "name:ja": "鰺ヶ沢町", "name:ja-Hira": "あじがさわまち", "name:ja-Latn": "Ajigasawa-machi", "name:ko": "아지가사와마치", "name:ru": "Адзигасава", "name:th": "อาจิงาซาวะ", "name:uk": "Адзіґасава", "name:zh": "鰺沢町", "name:zh-Hans": "鲹沢町", "name:zh-Hant": "鰺沢町", "ref": "023213", "type": "boundary", "wikidata": "Q1347560", "wikipedia": "ja:鰺ヶ沢町"}}, {"type": "relation", "id": 4107537, "center": {"lat": 40.5254135, "lon": 140.233896}, "tags": {"admin_level": "7", "boundary": "administrative", "name": "西目屋村", "name:en": "Nishimeya", "name:ja": "西目屋村", "name:ja-Hira": "にしめやむら", "name:ja-Latn": "Nishimeya-mura", "name:ko": "니시메야무라", "name:ru": "Нисимея", "name:th": "นิชิเมยะ", "name:uk": "Нісі-Мея", "name:zh": "西目屋村", "name:zh-Hans": "西目屋村", "name:zh-Hant": "西目屋村", "ref": "023434", "type": "boundary", "wikidata": "Q1347597", "wikipedia": "ja:西目屋村"}}, {"type": "relation", "id": 4107540, "center": {"lat": 40.6342458, "lon": 139.7006314}, "tags": {"admin_level": "7", "boundary": "administrative", "name": "深浦町", "name:en": "Fukaura", "name:ja": "深浦町", "name:ja-Hira": "ふかうらまち", "name:ja-Latn": "Fukaura-machi", "name:ko": "후카우라마치", "name:ru": "Фукаура", "name:th": "ฟูกาอูระ", "name:uk": "Фукаура", "name:zh": "深浦町", "name:zh-Hans": "深浦町", "name:zh-Hant": "深浦町", "ref": "023230", "type": "boundary", "wikidata": "Q1347642", "wikipedia": "ja:深浦町"}}, {"type": "relation", "id": 4107558, "center": {"lat": 40.644839, "lon": 140.539561}, "tags": {"admin_level": "7", "boundary": "administrative", "name": "田舎館村", "name:en": "Inakadate", "name:ja": "田舎館村", "name:ja-Hira": "いなかだてむら", "name:ja-Latn": "Inakadate-mura", "name:ko": "이나카다테무라", "name:pl": "Inakadate", "name:ru": "Инакадате", "name:th": "อินากาดาเตะ", "name:uk": "Інакадате", "name:zh": "田舍館村", "name:zh-Hans": "田舍馆村", "name:zh-Hant": "田舍館村", "ref": "023671", "type": "boundary", "wikidata": "Q1362354", "wikipedia": "ja:田舎館村"}}, {"type": "relation", "id": 4107676, "center": {"lat": 40.4735299, "lon": 140.5561315}, "tags": {"admin_level": "7", "boundary": "administrative", "name": "大鰐町", "name:en": "Owani", "name:ja": "大鰐町", "name:ja-Hira": "おおわにまち", "name:ja-Latn": "Ōwani-machi", "name:ko": "오와니마치", "name:pl": "Ōwani", "name:ru": "Овани", "name:th": "โอวานิ", "name:uk": "Овані", "name:zh": "大鰐町", "name:zh-Hans": "大鳄町", "name:zh-Hant": "大鰐町", "ref": "023621", "type": "boundary", "wikidata": "Q1347678", "wikipedia": "ja:大鰐町"}}, {"type": "relation", "id": 4107754, "center": {"lat": 40.449803, "lon": 141.1085655}, "tags": {"admin_level": "7", "boundary": "administrative", "name": "新郷村", "name:en": "Shingo", "name:fr": "Shingo", "name:ja": "新郷村", "name:ja-Hira": "しんごうむら", "name:ja-Latn": "Shingō-mura", "name:ko": "신고무라", "name:pl": "Shingō", "name:ru": "Синго", "name:th": "ชิงโง", "name:uk": "Сінґо", "name:zh": "新鄉村", "name:zh-Hans": "新乡村", "name:zh-Hant": "新鄉村", "ref": "024503", "type": "boundary", "wikidata": "Q44548", "wikipedia": "ja:新郷村"}}, {"type": "relation", "id": 4107760, "center": {"lat": 40.4176275, "lon": 141.3322535}, "tags": {"admin_level": "7", "boundary": "administrative", "name": "南部町", "name:en": "Nanbu", "name:ja": "南部町", "name:ja-Hira": "なんぶちょう", "name:ja-Latn": "Nanbu-chō", "name:ko": "난부초", "name:ru": "Намбу", "name:th": "นัมบุ", "name:uk": "Намбу", "name:zh": "南部町", "name:zh-Hans": "南部町", "name:zh-Hant": "南部町", "population": "17729", "ref": "024457", "type": "boundary", "wikidata": "Q1206409", "wikipedia": "ja:南部町 (青森県)"}}, {"type": "relation", "id": 4107781, "center": {"lat": 40.363315, "lon": 141.149244}, "tags": {"admin_level": "7", "boundary": "administrative", "name": "三戸町", "name:en": "Sannohe", "name:ja": "三戸町", "name:ja-Hira": "さんのへまち", "name:ja-Latn": "Sannohe-machi", "name:ko": "산노헤마치", "name:ru": "Саннохе", "name:th": "ซันโนเฮะ", "name:uk": "Саннохе", "name:zh": "三戶町", "name:zh-Hans": "三户町", "name:zh-Hant": "三戶町", "ref": "024414", "type": "boundary", "wikidata": "Q2358935", "wikipedia": "ja:三戸町"}}, {"type": "relation", "id": 4107791, "center": {"lat": 40.3070515, "lon": 141.0637125}, "tags": {"admin_level": "7", "boundary": "administrative", "name": "田子町", "name:en": "Takko", "name:ja": "田子町", "name:ja-Hira": "たっこまち", "name:ja-Latn": "Takko-machi", "name:ko": "닷코마치", "name:ru": "Такко", "name:th": "ทักโกะ", "name:uk": "Такко", "name:zh": "田子町", "name:zh-Hans": "田子町", "name:zh-Hant": "田子町", "ref": "024431", "type": "boundary", "wikidata": "Q1349168", "wikipedia": "ja:田子町"}}, {"type": "relation", "id": 4107946, "center": {"lat": 40.4801307, "lon": 141.7113663}, "tags": {"admin_level": "7", "boundary": "administrative", "name": "階上町", "name:en": "Hashikami", "name:ja": "階上町", "name:ja-Hira": "はしかみちょう", "name:ja-Latn": "Hashikami-chō", "name:ko": "하시카미초", "name:ru": "Хасиками", "name:th": "ฮาชิกามิ", "name:uk": "Хасікамі", "name:zh": "階上町", "name:zh-Hans": "阶上町", "name:zh-Hant": "階上町", "ref": "024465", "type": "boundary", "wikidata": "Q1349010", "wikipedia": "ja:階上町"}}]}